{
  "cols": 14,
  "rows": 13,
  "tile_w": 7,
  "tile_h": 12,
  "baseline": 10,
  "line_gap": 1,
  "space_w": 7,
  "glyphs": [
    {
      "chr": "\u0000",
      "lsb": 0,
      "adv": 7
    },
    {
      "chr": "!",
      "lsb": 2,
      "adv": 7
    },
    {
      "chr": "\"",
      "lsb": 0,
      "adv": 7
    },
    {
      "chr": "#",
      "lsb": 0,
      "adv": 7
    },
    {
      "chr": "$",
      "lsb": 0,
      "adv": 7
    },
    {
      "chr": "%",
      "lsb": 0,
      "adv": 7
    },
    {
      "chr": "&",
      "lsb": 0,
      "adv": 7
    },
    {
      "chr": "'",
      "lsb": 2,
      "adv": 7
    },
    {
      "chr": "(",
      "lsb": 1,
      "adv": 7
    },
    {
      "chr": ")",
      "lsb": 1,
      "adv": 7
    },
    {
      "chr": "*",
      "lsb": 0,
      "adv": 7
    },
    {
      "chr": "+",
      "lsb": 0,
      "adv": 7
    },
    {
      "chr": ",",
      "lsb": 1,
      "adv": 7
    },
    {
      "chr": "-",
      "lsb": 0,
      "adv": 7
    },
    {
      "chr": ".",
      "lsb": 2,
      "adv": 7
    },
    {
      "chr": "/",
      "lsb": 0,
      "adv": 7
    },
    {
      "chr": "0",
      "lsb": 0,
      "adv": 7
    },
    {
      "chr": "1",
      "lsb": 0,
      "adv": 7
    },
    {
      "chr": "2",
      "lsb": 0,
      "adv": 7
    },
    {
      "chr": "3",
      "lsb": 0,
      "adv": 7
    },
    {
      "chr": "4",
      "lsb": 0,
      "adv": 7
    },
    {
      "chr": "5",
      "lsb": 0,
      "adv": 7
    },
    {
      "chr": "6",
      "lsb": 0,
      "adv": 7
    },
    {
      "chr": "7",
      "lsb": 0,
      "adv": 7
    },
    {
      "chr": "8",
      "lsb": 0,
      "adv": 7
    },
    {
      "chr": "9",
      "lsb": 0,
      "adv": 7
    },
    {
      "chr": ":",
      "lsb": 2,
      "adv": 7
    },
    {
      "chr": ";",
      "lsb": 1,
      "adv": 7
    },
    {
      "chr": "<",
      "lsb": 1,
      "adv": 7
    },
    {
      "chr": "=",
      "lsb": 0,
      "adv": 7
    },
    {
      "chr": ">",
      "lsb": 1,
      "adv": 7
    },
    {
      "chr": "?",
      "lsb": 0,
      "adv": 7
    },
    {
      "chr": "@",
      "lsb": 0,
      "adv": 7
    },
    {
      "chr": "A",
      "lsb": 0,
      "adv": 7
    },
    {
      "chr": "B",
      "lsb": 0,
      "adv": 7
    },
    {
      "chr": "C",
      "lsb": 0,
      "adv": 7
    },
    {
      "chr": "D",
      "lsb": 0,
      "adv": 7
    },
    {
      "chr": "E",
      "lsb": 0,
      "adv": 7
    },
    {
      "chr": "F",
      "lsb": 0,
      "adv": 7
    },
    {
      "chr": "G",
      "lsb": 0,
      "adv": 7
    },
    {
      "chr": "H",
      "lsb": 0,
      "adv": 7
    },
    {
      "chr": "I",
      "lsb": 0,
      "adv": 7
    },
    {
      "chr": "J",
      "lsb": 0,
      "adv": 7
    },
    {
      "chr": "K",
      "lsb": 0,
      "adv": 7
    },
    {
      "chr": "L",
      "lsb": 0,
      "adv": 7
    },
    {
      "chr": "M",
      "lsb": 0,
      "adv": 7
    },
    {
      "chr": "N",
      "lsb": 0,
      "adv": 7
    },
    {
      "chr": "O",
      "lsb": 0,
      "adv": 7
    },
    {
      "chr": "P",
      "lsb": 0,
      "adv": 7
    },
    {
      "chr": "Q",
      "lsb": 0,
      "adv": 7
    },
    {
      "chr": "R",
      "lsb": 0,
      "adv": 7
    },
    {
      "chr": "S",
      "lsb": 0,
      "adv": 7
    },
    {
      "chr": "T",
      "lsb": 0,
      "adv": 7
    },
    {
      "chr": "U",
      "lsb": 0,
      "adv": 7
    },
    {
      "chr": "V",
      "lsb": 0,
      "adv": 7
    },
    {
      "chr": "W",
      "lsb": 0,
      "adv": 7
    },
    {
      "chr": "X",
      "lsb": 0,
      "adv": 7
    },
    {
      "chr": "Y",
      "lsb": 0,
      "adv": 7
    },
    {
      "chr": "Z",
      "lsb": 0,
      "adv": 7
    },
    {
      "chr": "[",
      "lsb": 1,
      "adv": 7
    },
    {
      "chr": "\\",
      "lsb": 0,
      "adv": 7
    },
    {
      "chr": "]",
      "lsb": 1,
      "adv": 7
    },
    {
      "chr": "^",
      "lsb": 0,
      "adv": 7
    },
    {
      "chr": "_",
      "lsb": 0,
      "adv": 7
    },
    {
      "chr": "`",
      "lsb": 1,
      "adv": 7
    },
    {
      "chr": "a",
      "lsb": 0,
      "adv": 7
    },
    {
      "chr": "b",
      "lsb": 0,
      "adv": 7
    },
    {
      "chr": "c",
      "lsb": 0,
      "adv": 7
    },
    {
      "chr": "d",
      "lsb": 0,
      "adv": 7
    },
    {
      "chr": "e",
      "lsb": 0,
      "adv": 7
    },
    {
      "chr": "f",
      "lsb": 0,
      "adv": 7
    },
    {
      "chr": "g",
      "lsb": 0,
      "adv": 7
    },
    {
      "chr": "h",
      "lsb": 0,
      "adv": 7
    },
    {
      "chr": "i",
      "lsb": 0,
      "adv": 7
    },
    {
      "chr": "j",
      "lsb": 0,
      "adv": 7
    },
    {
      "chr": "k",
      "lsb": 0,
      "adv": 7
    },
    {
      "chr": "l",
      "lsb": 0,
      "adv": 7
    },
    {
      "chr": "m",
      "lsb": 0,
      "adv": 7
    },
    {
      "chr": "n",
      "lsb": 0,
      "adv": 7
    },
    {
      "chr": "o",
      "lsb": 0,
      "adv": 7
    },
    {
      "chr": "p",
      "lsb": 0,
      "adv": 7
    },
    {
      "chr": "q",
      "lsb": 0,
      "adv": 7
    },
    {
      "chr": "r",
      "lsb": 0,
      "adv": 7
    },
    {
      "chr": "s",
      "lsb": 0,
      "adv": 7
    },
    {
      "chr": "t",
      "lsb": 0,
      "adv": 7
    },
    {
      "chr": "u",
      "lsb": 0,
      "adv": 7
    },
    {
      "chr": "v",
      "lsb": 0,
      "adv": 7
    },
    {
      "chr": "w",
      "lsb": 0,
      "adv": 7
    },
    {
      "chr": "x",
      "lsb": 0,
      "adv": 7
    },
    {
      "chr": "y",
      "lsb": 0,
      "adv": 7
    },
    {
      "chr": "z",
      "lsb": 0,
      "adv": 7
    },
    {
      "chr": "{",
      "lsb": 0,
      "adv": 7
    },
    {
      "chr": "|",
      "lsb": 2,
      "adv": 7
    },
    {
      "chr": "}",
      "lsb": 0,
      "adv": 7
    },
    {
      "chr": "~",
      "lsb": 0,
      "adv": 7
    },
    {
      "chr": "¡",
      "lsb": 2,
      "adv": 7
    },
    {
      "chr": "¢",
      "lsb": 0,
      "adv": 7
    },
    {
      "chr": "£",
      "lsb": 0,
      "adv": 7
    },
    {
      "chr": "¥",
      "lsb": 0,
      "adv": 7
    },
    {
      "chr": "©",
      "lsb": 0,
      "adv": 7
    },
    {
      "chr": "«",
      "lsb": 0,
      "adv": 7
    },
    {
      "chr": "®",
      "lsb": 0,
      "adv": 7
    },
    {
      "chr": "°",
      "lsb": 0,
      "adv": 7
    },
    {
      "chr": "»",
      "lsb": 0,
      "adv": 7
    },
    {
      "chr": "¿",
      "lsb": 0,
      "adv": 7
    },
    {
      "chr": "À",
      "lsb": 0,
      "adv": 7
    },
    {
      "chr": "Á",
      "lsb": 0,
      "adv": 7
    },
    {
      "chr": "Â",
      "lsb": 0,
      "adv": 7
    },
    {
      "chr": "Ã",
      "lsb": 0,
      "adv": 7
    },
    {
      "chr": "Ä",
      "lsb": 0,
      "adv": 7
    },
    {
      "chr": "Å",
      "lsb": 0,
      "adv": 7
    },
    {
      "chr": "Æ",
      "lsb": 0,
      "adv": 7
    },
    {
      "chr": "Ç",
      "lsb": 0,
      "adv": 7
    },
    {
      "chr": "È",
      "lsb": 0,
      "adv": 7
    },
    {
      "chr": "É",
      "lsb": 0,
      "adv": 7
    },
    {
      "chr": "Ê",
      "lsb": 0,
      "adv": 7
    },
    {
      "chr": "Ë",
      "lsb": 0,
      "adv": 7
    },
    {
      "chr": "Ì",
      "lsb": 0,
      "adv": 7
    },
    {
      "chr": "Í",
      "lsb": 0,
      "adv": 7
    },
    {
      "chr": "Î",
      "lsb": 0,
      "adv": 7
    },
    {
      "chr": "Ï",
      "lsb": 0,
      "adv": 7
    },
    {
      "chr": "Ñ",
      "lsb": 0,
      "adv": 7
    },
    {
      "chr": "Ò",
      "lsb": 0,
      "adv": 7
    },
    {
      "chr": "Ó",
      "lsb": 0,
      "adv": 7
    },
    {
      "chr": "Ô",
      "lsb": 0,
      "adv": 7
    },
    {
      "chr": "Õ",
      "lsb": 0,
      "adv": 7
    },
    {
      "chr": "Ö",
      "lsb": 0,
      "adv": 7
    },
    {
      "chr": "Ù",
      "lsb": 0,
      "adv": 7
    },
    {
      "chr": "Ú",
      "lsb": 0,
      "adv": 7
    },
    {
      "chr": "Û",
      "lsb": 0,
      "adv": 7
    },
    {
      "chr": "Ü",
      "lsb": 0,
      "adv": 7
    },
    {
      "chr": "ß",
      "lsb": 0,
      "adv": 7
    },
    {
      "chr": "à",
      "lsb": 0,
      "adv": 7
    },
    {
      "chr": "á",
      "lsb": 0,
      "adv": 7
    },
    {
      "chr": "â",
      "lsb": 0,
      "adv": 7
    },
    {
      "chr": "ã",
      "lsb": 0,
      "adv": 7
    },
    {
      "chr": "ä",
      "lsb": 0,
      "adv": 7
    },
    {
      "chr": "å",
      "lsb": 0,
      "adv": 7
    },
    {
      "chr": "æ",
      "lsb": 0,
      "adv": 7
    },
    {
      "chr": "ç",
      "lsb": 0,
      "adv": 7
    },
    {
      "chr": "è",
      "lsb": 0,
      "adv": 7
    },
    {
      "chr": "é",
      "lsb": 0,
      "adv": 7
    },
    {
      "chr": "ê",
      "lsb": 0,
      "adv": 7
    },
    {
      "chr": "ë",
      "lsb": 0,
      "adv": 7
    },
    {
      "chr": "ì",
      "lsb": 0,
      "adv": 7
    },
    {
      "chr": "í",
      "lsb": 0,
      "adv": 7
    },
    {
      "chr": "î",
      "lsb": 0,
      "adv": 7
    },
    {
      "chr": "ï",
      "lsb": 0,
      "adv": 7
    },
    {
      "chr": "ñ",
      "lsb": 0,
      "adv": 7
    },
    {
      "chr": "ò",
      "lsb": 0,
      "adv": 7
    },
    {
      "chr": "ó",
      "lsb": 0,
      "adv": 7
    },
    {
      "chr": "ô",
      "lsb": 0,
      "adv": 7
    },
    {
      "chr": "õ",
      "lsb": 0,
      "adv": 7
    },
    {
      "chr": "ö",
      "lsb": 0,
      "adv": 7
    },
    {
      "chr": "ù",
      "lsb": 0,
      "adv": 7
    },
    {
      "chr": "ú",
      "lsb": 0,
      "adv": 7
    },
    {
      "chr": "û",
      "lsb": 0,
      "adv": 7
    },
    {
      "chr": "ü",
      "lsb": 0,
      "adv": 7
    },
    {
      "chr": "ÿ",
      "lsb": 0,
      "adv": 7
    },
    {
      "chr": "Œ",
      "lsb": 0,
      "adv": 7
    },
    {
      "chr": "œ",
      "lsb": 0,
      "adv": 7
    },
    {
      "chr": "Ÿ",
      "lsb": 0,
      "adv": 7
    },
    {
      "chr": "ẞ",
      "lsb": 0,
      "adv": 7
    },
    {
      "chr": "–",
      "lsb": 0,
      "adv": 7
    },
    {
      "chr": "—",
      "lsb": 0,
      "adv": 7
    },
    {
      "chr": "‘",
      "lsb": 1,
      "adv": 7
    },
    {
      "chr": "’",
      "lsb": 1,
      "adv": 7
    },
    {
      "chr": "‚",
      "lsb": 1,
      "adv": 7
    },
    {
      "chr": "“",
      "lsb": 0,
      "adv": 7
    },
    {
      "chr": "”",
      "lsb": 0,
      "adv": 7
    },
    {
      "chr": "„",
      "lsb": 0,
      "adv": 7
    },
    {
      "chr": "•",
      "lsb": 1,
      "adv": 7
    },
    {
      "chr": "…",
      "lsb": 0,
      "adv": 7
    },
    {
      "chr": "‹",
      "lsb": 1,
      "adv": 7
    },
    {
      "chr": "›",
      "lsb": 1,
      "adv": 7
    },
    {
      "chr": "€",
      "lsb": 0,
      "adv": 7
    },
    {
      "chr": "™",
      "lsb": 0,
      "adv": 7
    }
  ]
}